ruuvitag_sensor/__init__.py
ruuvitag_sensor/__main__.py
ruuvitag_sensor/data_formats.py
ruuvitag_sensor/decoder.py
ruuvitag_sensor/log.py
ruuvitag_sensor/ruuvi.py
ruuvitag_sensor/ruuvi_rx.py
ruuvitag_sensor/ruuvi_types.py
ruuvitag_sensor/ruuvitag.py
ruuvitag_sensor/adapters/__init__.py
ruuvitag_sensor/adapters/bleak_ble.py
ruuvitag_sensor/adapters/bleson.py
ruuvitag_sensor/adapters/dummy.py
ruuvitag_sensor/adapters/nix_hci.py
ruuvitag_sensor/adapters/nix_hci_file.py
ruuvitag_sensor/adapters/utils.py
ruuvitag_sensor/adapters/development/__init__.py
ruuvitag_sensor/adapters/development/dev_bleak_scanner.py
ruuvitag_sensor-4.0.0.dist-info/licenses/LICENSE
ruuvitag_sensor-4.0.0.dist-info/METADATA
ruuvitag_sensor-4.0.0.dist-info/WHEEL
ruuvitag_sensor-4.0.0.dist-info/top_level.txt
ruuvitag_sensor-4.0.0.dist-info/RECORD
