Metadata-Version: 2.4
Name: ruuvitag_sensor
Version: 4.0.0
Summary: Find RuuviTag sensors and get decoded data from selected sensors
Author-email: Tomi Tuhkanen <tomi.tuhkanen@iki.fi>
License-Expression: MIT
Project-URL: homepage, https://github.com/ttu/ruuvitag-sensor
Project-URL: documentation, https://ttu.github.io/ruuvitag-sensor/
Project-URL: source, https://github.com/ttu/ruuvitag-sensor
Project-URL: changelog, https://github.com/ttu/ruuvitag-sensor/blob/master/CHANGELOG.md
Project-URL: issues, https://github.com/ttu/ruuvitag-sensor/issues
Keywords: RuuviTag,BLE,Bluetooth,IoT,Sensor
Classifier: Programming Language :: Python
Classifier: Programming Language :: Python :: 3.10
Classifier: Programming Language :: Python :: 3.11
Classifier: Programming Language :: Python :: 3.12
Classifier: Programming Language :: Python :: 3.13
Classifier: Programming Language :: Python :: 3.14
Classifier: Operating System :: OS Independent
Classifier: Intended Audience :: Developers
Classifier: Development Status :: 5 - Production/Stable
Classifier: Framework :: AsyncIO
Classifier: Framework :: Pytest
Requires-Python: >=3.10
License-File: LICENSE
Requires-Dist: reactivex
Requires-Dist: ptyprocess; platform_system == "Linux"
Requires-Dist: bleak
Provides-Extra: dev
Requires-Dist: pytest; extra == "dev"
Requires-Dist: pytest-asyncio; extra == "dev"
Requires-Dist: ruff<0.15.0,>=0.14.0; extra == "dev"
Requires-Dist: mypy<2.0.0,>=1.0.0; extra == "dev"
Dynamic: license-file
